<map LengthX="18" LengthY="12" LengthZ="1" DefaultTile="0" Style="2" Function="1" ShapeName="test4">
  <element X="0" Y="0" Z="0" data="-1" />
  <element X="0" Y="1" Z="0" data="-1" />
  <element X="0" Y="2" Z="0" data="-1" />
  <element X="0" Y="3" Z="0" data="-1" />
  <element X="0" Y="4" Z="0" data="-1" />
  <element X="0" Y="5" Z="0" data="-2" />
  <element X="0" Y="6" Z="0" data="-2" />
  <element X="0" Y="7" Z="0" data="-2" />
  <element X="0" Y="8" Z="0" data="5" />
  <element X="0" Y="9" Z="0" data="-2" />
  <element X="0" Y="10" Z="0" data="-2" />
  <element X="0" Y="11" Z="0" data="-2" />
  <element X="1" Y="0" Z="0" data="-1" />
  <element X="1" Y="1" Z="0" data="-1" />
  <element X="1" Y="2" Z="0" data="-1" />
  <element X="1" Y="3" Z="0" data="-1" />
  <element X="1" Y="4" Z="0" data="-1" />
  <element X="1" Y="5" Z="0" data="-2" />
  <element X="1" Y="6" Z="0" data="10" />
  <element X="1" Y="7" Z="0" data="10" />
  <element X="1" Y="8" Z="0" data="10" />
  <element X="1" Y="9" Z="0" data="10" />
  <element X="1" Y="10" Z="0" data="10" />
  <element X="1" Y="11" Z="0" data="-2" />
  <element X="2" Y="0" Z="0" data="-1" />
  <element X="2" Y="1" Z="0" data="-1" />
  <element X="2" Y="2" Z="0" data="-1" />
  <element X="2" Y="3" Z="0" data="-1" />
  <element X="2" Y="4" Z="0" data="-1" />
  <element X="2" Y="5" Z="0" data="-2" />
  <element X="2" Y="6" Z="0" data="-2" />
  <element X="2" Y="7" Z="0" data="-3" />
  <element X="2" Y="8" Z="0" data="-3" />
  <element X="2" Y="9" Z="0" data="-3" />
  <element X="2" Y="10" Z="0" data="10" />
  <element X="2" Y="11" Z="0" data="-2" />
  <element X="3" Y="0" Z="0" data="-1" />
  <element X="3" Y="1" Z="0" data="-1" />
  <element X="3" Y="2" Z="0" data="-1" />
  <element X="3" Y="3" Z="0" data="-1" />
  <element X="3" Y="4" Z="0" data="-1" />
  <element X="3" Y="5" Z="0" data="-2" />
  <element X="3" Y="6" Z="0" data="-2" />
  <element X="3" Y="7" Z="0" data="-3" />
  <element X="3" Y="8" Z="0" data="0" />
  <element X="3" Y="9" Z="0" data="-3" />
  <element X="3" Y="10" Z="0" data="10" />
  <element X="3" Y="11" Z="0" data="-2" />
  <element X="4" Y="0" Z="0" data="-1" />
  <element X="4" Y="1" Z="0" data="-1" />
  <element X="4" Y="2" Z="0" data="-1" />
  <element X="4" Y="3" Z="0" data="-1" />
  <element X="4" Y="4" Z="0" data="-1" />
  <element X="4" Y="5" Z="0" data="-2" />
  <element X="4" Y="6" Z="0" data="-2" />
  <element X="4" Y="7" Z="0" data="-3" />
  <element X="4" Y="8" Z="0" data="-3" />
  <element X="4" Y="9" Z="0" data="-3" />
  <element X="4" Y="10" Z="0" data="10" />
  <element X="4" Y="11" Z="0" data="-2" />
  <element X="5" Y="0" Z="0" data="2" />
  <element X="5" Y="1" Z="0" data="2" />
  <element X="5" Y="2" Z="0" data="2" />
  <element X="5" Y="3" Z="0" data="2" />
  <element X="5" Y="4" Z="0" data="2" />
  <element X="5" Y="5" Z="0" data="-2" />
  <element X="5" Y="6" Z="0" data="9" />
  <element X="5" Y="7" Z="0" data="9" />
  <element X="5" Y="8" Z="0" data="9" />
  <element X="5" Y="9" Z="0" data="9" />
  <element X="5" Y="10" Z="0" data="9" />
  <element X="5" Y="11" Z="0" data="-2" />
  <element X="6" Y="0" Z="0" data="2" />
  <element X="6" Y="1" Z="0" data="2" />
  <element X="6" Y="2" Z="0" data="2" />
  <element X="6" Y="3" Z="0" data="2" />
  <element X="6" Y="4" Z="0" data="2" />
  <element X="6" Y="5" Z="0" data="-2" />
  <element X="6" Y="6" Z="0" data="-2" />
  <element X="6" Y="7" Z="0" data="-2" />
  <element X="6" Y="8" Z="0" data="-2" />
  <element X="6" Y="9" Z="0" data="-2" />
  <element X="6" Y="10" Z="0" data="-2" />
  <element X="6" Y="11" Z="0" data="-2" />
  <element X="7" Y="0" Z="0" data="2" />
  <element X="7" Y="1" Z="0" data="2" />
  <element X="7" Y="2" Z="0" data="2" />
  <element X="7" Y="3" Z="0" data="2" />
  <element X="7" Y="4" Z="0" data="2" />
  <element X="7" Y="5" Z="0" data="2" />
  <element X="7" Y="6" Z="0" data="-2" />
  <element X="7" Y="7" Z="0" data="2" />
  <element X="7" Y="8" Z="0" data="2" />
  <element X="7" Y="9" Z="0" data="2" />
  <element X="7" Y="10" Z="0" data="2" />
  <element X="7" Y="11" Z="0" data="-2" />
  <element X="8" Y="0" Z="0" data="5" />
  <element X="8" Y="1" Z="0" data="2" />
  <element X="8" Y="2" Z="0" data="2" />
  <element X="8" Y="3" Z="0" data="2" />
  <element X="8" Y="4" Z="0" data="2" />
  <element X="8" Y="5" Z="0" data="2" />
  <element X="8" Y="6" Z="0" data="4" />
  <element X="8" Y="7" Z="0" data="2" />
  <element X="8" Y="8" Z="0" data="2" />
  <element X="8" Y="9" Z="0" data="2" />
  <element X="8" Y="10" Z="0" data="2" />
  <element X="8" Y="11" Z="0" data="-2" />
  <element X="9" Y="0" Z="0" data="-2" />
  <element X="9" Y="1" Z="0" data="2" />
  <element X="9" Y="2" Z="0" data="2" />
  <element X="9" Y="3" Z="0" data="2" />
  <element X="9" Y="4" Z="0" data="2" />
  <element X="9" Y="5" Z="0" data="2" />
  <element X="9" Y="6" Z="0" data="-2" />
  <element X="9" Y="7" Z="0" data="2" />
  <element X="9" Y="8" Z="0" data="2" />
  <element X="9" Y="9" Z="0" data="2" />
  <element X="9" Y="10" Z="0" data="2" />
  <element X="9" Y="11" Z="0" data="-2" />
  <element X="10" Y="0" Z="0" data="-2" />
  <element X="10" Y="1" Z="0" data="2" />
  <element X="10" Y="2" Z="0" data="2" />
  <element X="10" Y="3" Z="0" data="2" />
  <element X="10" Y="4" Z="0" data="2" />
  <element X="10" Y="5" Z="0" data="2" />
  <element X="10" Y="6" Z="0" data="-2" />
  <element X="10" Y="7" Z="0" data="2" />
  <element X="10" Y="8" Z="0" data="2" />
  <element X="10" Y="9" Z="0" data="2" />
  <element X="10" Y="10" Z="0" data="2" />
  <element X="10" Y="11" Z="0" data="-2" />
  <element X="11" Y="0" Z="0" data="-2" />
  <element X="11" Y="1" Z="0" data="2" />
  <element X="11" Y="2" Z="0" data="2" />
  <element X="11" Y="3" Z="0" data="2" />
  <element X="11" Y="4" Z="0" data="2" />
  <element X="11" Y="5" Z="0" data="-2" />
  <element X="11" Y="6" Z="0" data="-2" />
  <element X="11" Y="7" Z="0" data="-2" />
  <element X="11" Y="8" Z="0" data="-2" />
  <element X="11" Y="9" Z="0" data="-2" />
  <element X="11" Y="10" Z="0" data="-2" />
  <element X="11" Y="11" Z="0" data="-2" />
  <element X="12" Y="0" Z="0" data="-2" />
  <element X="12" Y="1" Z="0" data="-2" />
  <element X="12" Y="2" Z="0" data="-2" />
  <element X="12" Y="3" Z="0" data="-2" />
  <element X="12" Y="4" Z="0" data="-2" />
  <element X="12" Y="5" Z="0" data="-2" />
  <element X="12" Y="6" Z="0" data="10" />
  <element X="12" Y="7" Z="0" data="10" />
  <element X="12" Y="8" Z="0" data="10" />
  <element X="12" Y="9" Z="0" data="10" />
  <element X="12" Y="10" Z="0" data="10" />
  <element X="12" Y="11" Z="0" data="-2" />
  <element X="13" Y="0" Z="0" data="-1" />
  <element X="13" Y="1" Z="0" data="-1" />
  <element X="13" Y="2" Z="0" data="-1" />
  <element X="13" Y="3" Z="0" data="-1" />
  <element X="13" Y="4" Z="0" data="-1" />
  <element X="13" Y="5" Z="0" data="-2" />
  <element X="13" Y="6" Z="0" data="-2" />
  <element X="13" Y="7" Z="0" data="-3" />
  <element X="13" Y="8" Z="0" data="-3" />
  <element X="13" Y="9" Z="0" data="-3" />
  <element X="13" Y="10" Z="0" data="10" />
  <element X="13" Y="11" Z="0" data="-2" />
  <element X="14" Y="0" Z="0" data="-1" />
  <element X="14" Y="1" Z="0" data="-1" />
  <element X="14" Y="2" Z="0" data="-1" />
  <element X="14" Y="3" Z="0" data="-1" />
  <element X="14" Y="4" Z="0" data="-1" />
  <element X="14" Y="5" Z="0" data="-2" />
  <element X="14" Y="6" Z="0" data="-2" />
  <element X="14" Y="7" Z="0" data="-3" />
  <element X="14" Y="8" Z="0" data="1" />
  <element X="14" Y="9" Z="0" data="-3" />
  <element X="14" Y="10" Z="0" data="10" />
  <element X="14" Y="11" Z="0" data="-2" />
  <element X="15" Y="0" Z="0" data="-1" />
  <element X="15" Y="1" Z="0" data="-1" />
  <element X="15" Y="2" Z="0" data="-1" />
  <element X="15" Y="3" Z="0" data="-1" />
  <element X="15" Y="4" Z="0" data="-1" />
  <element X="15" Y="5" Z="0" data="-2" />
  <element X="15" Y="6" Z="0" data="-2" />
  <element X="15" Y="7" Z="0" data="-3" />
  <element X="15" Y="8" Z="0" data="-3" />
  <element X="15" Y="9" Z="0" data="-3" />
  <element X="15" Y="10" Z="0" data="10" />
  <element X="15" Y="11" Z="0" data="-2" />
  <element X="16" Y="0" Z="0" data="-1" />
  <element X="16" Y="1" Z="0" data="-1" />
  <element X="16" Y="2" Z="0" data="-1" />
  <element X="16" Y="3" Z="0" data="-1" />
  <element X="16" Y="4" Z="0" data="-1" />
  <element X="16" Y="5" Z="0" data="-2" />
  <element X="16" Y="6" Z="0" data="10" />
  <element X="16" Y="7" Z="0" data="10" />
  <element X="16" Y="8" Z="0" data="10" />
  <element X="16" Y="9" Z="0" data="10" />
  <element X="16" Y="10" Z="0" data="10" />
  <element X="16" Y="11" Z="0" data="-2" />
  <element X="17" Y="0" Z="0" data="-1" />
  <element X="17" Y="1" Z="0" data="-1" />
  <element X="17" Y="2" Z="0" data="-1" />
  <element X="17" Y="3" Z="0" data="-1" />
  <element X="17" Y="4" Z="0" data="-1" />
  <element X="17" Y="5" Z="0" data="-2" />
  <element X="17" Y="6" Z="0" data="-2" />
  <element X="17" Y="7" Z="0" data="-2" />
  <element X="17" Y="8" Z="0" data="5" />
  <element X="17" Y="9" Z="0" data="-2" />
  <element X="17" Y="10" Z="0" data="-2" />
  <element X="17" Y="11" Z="0" data="-2" />
</map>